McSixAI/__init__.py
McSixAI/__main__.py
McSixAI/cli.py
McSixAI/commands.py
McSixAI/config.py
McSixAI/file_manager.py
McSixAI/main.py
McSixAI/openrouter.py
McSixAI/utils.py
mcsixai-0.1.6.dist-info/METADATA
mcsixai-0.1.6.dist-info/WHEEL
mcsixai-0.1.6.dist-info/entry_points.txt
mcsixai-0.1.6.dist-info/top_level.txt
mcsixai-0.1.6.dist-info/RECORD
